amsdal_ml/Third-Party Materials - AMSDAL Dependencies - License Notices.md
amsdal_ml/__about__.py
amsdal_ml/__init__.py
amsdal_ml/app.py
amsdal_ml/ml_config.py
amsdal_ml/py.typed
amsdal_ml/agents/__init__.py
amsdal_ml/agents/agent.py
amsdal_ml/agents/default_qa_agent.py
amsdal_ml/agents/functional_calling_agent.py
amsdal_ml/agents/mcp_client_tool.py
amsdal_ml/agents/python_tool.py
amsdal_ml/agents/retriever_tool.py
amsdal_ml/agents/tool_adapters.py
amsdal_ml/fileio/__init__.py
amsdal_ml/fileio/base_loader.py
amsdal_ml/fileio/openai_loader.py
amsdal_ml/mcp_client/__init__.py
amsdal_ml/mcp_client/base.py
amsdal_ml/mcp_client/http_client.py
amsdal_ml/mcp_client/stdio_client.py
amsdal_ml/mcp_server/__init__.py
amsdal_ml/mcp_server/server_retriever_stdio.py
amsdal_ml/migrations/0000_initial.py
amsdal_ml/ml_ingesting/__init__.py
amsdal_ml/ml_ingesting/default_ingesting.py
amsdal_ml/ml_ingesting/embedding_data.py
amsdal_ml/ml_ingesting/ingesting.py
amsdal_ml/ml_ingesting/model_ingester.py
amsdal_ml/ml_ingesting/openai_ingesting.py
amsdal_ml/ml_ingesting/pipeline.py
amsdal_ml/ml_ingesting/pipeline_interface.py
amsdal_ml/ml_ingesting/types.py
amsdal_ml/ml_ingesting/embedders/__init__.py
amsdal_ml/ml_ingesting/embedders/embedder.py
amsdal_ml/ml_ingesting/embedders/openai_embedder.py
amsdal_ml/ml_ingesting/loaders/__init__.py
amsdal_ml/ml_ingesting/loaders/folder_loader.py
amsdal_ml/ml_ingesting/loaders/loader.py
amsdal_ml/ml_ingesting/loaders/pdf_loader.py
amsdal_ml/ml_ingesting/loaders/text_loader.py
amsdal_ml/ml_ingesting/processors/__init__.py
amsdal_ml/ml_ingesting/processors/cleaner.py
amsdal_ml/ml_ingesting/processors/text_cleaner.py
amsdal_ml/ml_ingesting/splitters/__init__.py
amsdal_ml/ml_ingesting/splitters/splitter.py
amsdal_ml/ml_ingesting/splitters/token_splitter.py
amsdal_ml/ml_ingesting/stores/__init__.py
amsdal_ml/ml_ingesting/stores/embedding_data.py
amsdal_ml/ml_ingesting/stores/store.py
amsdal_ml/ml_models/__init__.py
amsdal_ml/ml_models/models.py
amsdal_ml-0.2.2.dist-info/METADATA
amsdal_ml-0.2.2.dist-info/WHEEL
amsdal_ml-0.2.2.dist-info/RECORD
